giteapy
test
