Metadata-Version: 2.1
Name: giteapy
Version: 1.0.7
Summary: Python SDK for Gitea - A painless, self-hosted Git service
Home-page: https://github.com/dblueai/giteapy
Author-email: rh@dblue.ai
License: UNKNOWN
Keywords: gitea,git
Platform: UNKNOWN
Classifier: Programming Language :: Python
Classifier: Programming Language :: Python :: 2
Classifier: Programming Language :: Python :: 2.7
Classifier: Programming Language :: Python :: 3
Classifier: Programming Language :: Python :: 3.5
Classifier: Programming Language :: Python :: 3.6
Classifier: Programming Language :: Python :: 3.7
Classifier: Operating System :: OS Independent
Classifier: Intended Audience :: Developers
